<?xml version="1.0"?>
<!DOCTYPE hibernate-mapping PUBLIC "-//Hibernate/Hibernate Mapping DTD 3.0//EN"
"http://www.hibernate.org/dtd/hibernate-mapping-3.0.dtd">
<!-- Generated 19-jul-2019 9:58:34 by Hibernate Tools 4.3.1 -->
<hibernate-mapping>
    <class name="entidades.Cargo" table="cargo" catalog="mascota" optimistic-lock="version">
        <id name="idCargo" type="string">
            <column name="idCargo" length="100" />
            <generator class="assigned" />
        </id>
        <property name="descripcion" type="string">
            <column name="descripcion" length="200" not-null="true" />
        </property>
        <property name="estado" type="string">
            <column name="estado" length="200" not-null="true" />
        </property>
    </class>
</hibernate-mapping>
